amend/__init__.py
amend/built_in/__init__.py
amend/built_in/mappings/__init__.py
amend/built_in/mappings/data_mappings.py
amend/built_in/numbers/__init__.py
amend/built_in/numbers/integers.py
amend/built_in/numbers/real_numbers.py
amend/built_in/sequences/__init__.py
amend/built_in/sequences/data_sequences.py
amend/built_in/sequences/sequence_containers.py
amend/built_in/sets/__init__.py
amend/built_in/sets/data_sets.py
amend/standard/__init__.py
amend/standard/paths.py
amend/standard/temporals.py
amend/testing/__init__.py
amend/testing/unit/__init__.py
amend/testing/unit/built_in/__init__.py
amend/testing/unit/built_in/mappings/__init__.py
amend/testing/unit/built_in/mappings/test_data_mappings.py
amend/testing/unit/built_in/numbers/__init__.py
amend/testing/unit/built_in/numbers/test_integers.py
amend/testing/unit/built_in/numbers/test_real_numbers.py
amend/testing/unit/built_in/sequences/__init__.py
amend/testing/unit/built_in/sequences/test_data_sequences.py
amend/testing/unit/built_in/sets/__init__.py
amend/testing/unit/built_in/sets/test_data_sets.py
amend/testing/unit/standard/__init__.py
amend/testing/unit/standard/test_paths.py
amend/testing/unit/standard/test_temporals.py
amend/testing/unit/utilities/__init__.py
amend/testing/unit/utilities/test_normalization.py
amend/utilities/__init__.py
amend/utilities/normalization.py
amend-0.3.1.dist-info/licenses/LICENSE
amend-0.3.1.dist-info/METADATA
amend-0.3.1.dist-info/WHEEL
amend-0.3.1.dist-info/top_level.txt
amend-0.3.1.dist-info/RECORD
