Metadata-Version: 2.4
Name: amend
Version: 0.3.1
Summary: Amend: Ensure your values are right
Author-email: Miljenko Šuflaj <suflajmob@gmail.com>
Maintainer-email: Miljenko Šuflaj <suflajmob@gmail.com>
Project-URL: Homepage, https://github.com/suflaj/amend
Project-URL: Repository, https://github.com/suflaj/amend.git
Project-URL: Issues, https://github.com/suflaj/amend/issues
Keywords: amend,validation,correction,processing
Classifier: Development Status :: 4 - Beta
Classifier: Intended Audience :: Developers
Classifier: Intended Audience :: Education
Classifier: License :: OSI Approved :: Apache Software License
Classifier: Natural Language :: English
Classifier: Operating System :: OS Independent
Classifier: Programming Language :: Python :: 3 :: Only
Classifier: Programming Language :: Python :: 3.10
Classifier: Programming Language :: Python :: 3.11
Classifier: Programming Language :: Python :: 3.12
Classifier: Programming Language :: Python :: 3.13
Classifier: Programming Language :: Python :: 3.14
Classifier: Topic :: Scientific/Engineering
Classifier: Topic :: Scientific/Engineering :: Information Analysis
Classifier: Topic :: Software Development
Classifier: Topic :: Software Development :: Quality Assurance
Classifier: Topic :: Software Development :: Testing
Classifier: Topic :: Software Development :: Testing :: Acceptance
Classifier: Topic :: Utilities
Requires-Python: >=3.8
License-File: LICENSE
Dynamic: license-file
